Workbook

Sheet Annahmen
A1: KORA Safety — Abo-Modell Anbieterseite
A2: Alle blauen Zellen sind Eingaben. Schwarze Zellen sind Formeln — nicht überschreiben.
A4: MARKT
A5: Wach- und Sicherheitsunternehmen in DE | B5: 5330 | C5: Destatis, WZ 80.1, Stand Sept. 2023
A6: davon Top 25 (eigener Vertrieb, nicht adressierbar) | B6: 25 | C6: Lünendonk-Liste 2026
A7: Realistisch adressierbar (Anteil) | B7: 0.45 | C7: ANNAHME: Betriebe mit Event-/Kurzfristgeschäft. Rahmenvertrags-Werkschutz kommt nicht auf eine Plattform.
A8: Zielgruppe gesamt | B8: =ROUND((B5-B6)*B7,0) | C8: Formel
A10: PREIS
A11: Abopreis pro Anbieter / Monat | B11: 99 | C11: Netto, zzgl. USt.
A12: Jahresumsatz pro Anbieter | B12: =B11*12 | C12: Formel
A14: WACHSTUM
A15: Neukunden Monat 1 | B15: 5 | C15: ANNAHME: manuelle Akquise per Telefon
A16: Monatliches Wachstum der Neukunden | B16: 0.15 | C16: ANNAHME: 15 % mehr Neuabschlüsse pro Monat
A17: Obergrenze Neukunden / Monat | B17: 60 | C17: ANNAHME: Kapazitätsgrenze ohne größeres Vertriebsteam
A19: ABWANDERUNG
A20: Monatliche Churn-Rate | B20: 0.04 | C20: ANNAHME: 4 % im KMU-Segment bei monatlicher Kündbarkeit. Kritischste Zahl im Modell.
A21: Rechnerische Kundenlebensdauer (Monate) | B21: =1/B20 | C21: Formel: 1 / Churn
A22: Lifetime Value je Anbieter | B22: =B11*B21 | C22: Formel
A24: AKQUISE
A25: Kosten pro Neukunde (CAC) | B25: 250 | C25: ANNAHME: Mix aus Eigenakquise und Paid Ads
A26: Amortisationsdauer (Monate) | B26: =B25/B11 | C26: Formel: CAC / Preis
A27: LTV / CAC | B27: =B22/B25 | C27: Formel. Unter 3,0 ist das Modell nicht tragfähig.

Sheet Projektion
A1: 36-Monats-Projektion
A3: Monat | B3: Neukunden | C3: Kündigungen | D3: Aktive Abos | E3: MRR | F3: ARR | G3: Akquisekosten | H3: Deckungsbeitrag kumuliert | I3: Marktdurchdringung | K3: Eckwerte
A4: 1 | B4: =MIN(Annahmen!$B$17,ROUND(Annahmen!$B$15*(1+Annahmen!$B$16)^(1-1),0)) | C4: 0 | D4: =B4-C4 | E4: =D4*Annahmen!$B$11 | F4: =E4*12 | G4: =B4*Annahmen!$B$25 | H4: =E4-G4 | I4: =D4/Annahmen!$B$8 | K4: ARR nach 12 Monaten | L4: =F15
A5: 2 | B5: =MIN(Annahmen!$B$17,ROUND(Annahmen!$B$15*(1+Annahmen!$B$16)^(2-1),0)) | C5: =ROUND(D4*Annahmen!$B$20,0) | D5: =D4+B5-C5 | E5: =D5*Annahmen!$B$11 | F5: =E5*12 | G5: =B5*Annahmen!$B$25 | H5: =H4+E5-G5 | I5: =D5/Annahmen!$B$8 | K5: ARR nach 24 Monaten | L5: =F27
A6: 3 | B6: =MIN(Annahmen!$B$17,ROUND(Annahmen!$B$15*(1+Annahmen!$B$16)^(3-1),0)) | C6: =ROUND(D5*Annahmen!$B$20,0) | D6: =D5+B6-C6 | E6: =D6*Annahmen!$B$11 | F6: =E6*12 | G6: =B6*Annahmen!$B$25 | H6: =H5+E6-G6 | I6: =D6/Annahmen!$B$8 | K6: ARR nach 36 Monaten | L6: =F39
A7: 4 | B7: =MIN(Annahmen!$B$17,ROUND(Annahmen!$B$15*(1+Annahmen!$B$16)^(4-1),0)) | C7: =ROUND(D6*Annahmen!$B$20,0) | D7: =D6+B7-C7 | E7: =D7*Annahmen!$B$11 | F7: =E7*12 | G7: =B7*Annahmen!$B$25 | H7: =H6+E7-G7 | I7: =D7/Annahmen!$B$8 | K7: Aktive Abos nach 36 Monaten | L7: =D39
A8: 5 | B8: =MIN(Annahmen!$B$17,ROUND(Annahmen!$B$15*(1+Annahmen!$B$16)^(5-1),0)) | C8: =ROUND(D7*Annahmen!$B$20,0) | D8: =D7+B8-C8 | E8: =D8*Annahmen!$B$11 | F8: =E8*12 | G8: =B8*Annahmen!$B$25 | H8: =H7+E8-G8 | I8: =D8/Annahmen!$B$8 | K8: Deckungsbeitrag kumuliert (36 M.) | L8: =H39
A9: 6 | B9: =MIN(Annahmen!$B$17,ROUND(Annahmen!$B$15*(1+Annahmen!$B$16)^(6-1),0)) | C9: =ROUND(D8*Annahmen!$B$20,0) | D9: =D8+B9-C9 | E9: =D9*Annahmen!$B$11 | F9: =E9*12 | G9: =B9*Annahmen!$B$25 | H9: =H8+E9-G9 | I9: =D9/Annahmen!$B$8 | K9: Marktdurchdringung nach 36 Monaten | L9: =I39
A10: 7 | B10: =MIN(Annahmen!$B$17,ROUND(Annahmen!$B$15*(1+Annahmen!$B$16)^(7-1),0)) | C10: =ROUND(D9*Annahmen!$B$20,0) | D10: =D9+B10-C10 | E10: =D10*Annahmen!$B$11 | F10: =E10*12 | G10: =B10*Annahmen!$B$25 | H10: =H9+E10-G10 | I10: =D10/Annahmen!$B$8
A11: 8 | B11: =MIN(Annahmen!$B$17,ROUND(Annahmen!$B$15*(1+Annahmen!$B$16)^(8-1),0)) | C11: =ROUND(D10*Annahmen!$B$20,0) | D11: =D10+B11-C11 | E11: =D11*Annahmen!$B$11 | F11: =E11*12 | G11: =B11*Annahmen!$B$25 | H11: =H10+E11-G11 | I11: =D11/Annahmen!$B$8
A12: 9 | B12: =MIN(Annahmen!$B$17,ROUND(Annahmen!$B$15*(1+Annahmen!$B$16)^(9-1),0)) | C12: =ROUND(D11*Annahmen!$B$20,0) | D12: =D11+B12-C12 | E12: =D12*Annahmen!$B$11 | F12: =E12*12 | G12: =B12*Annahmen!$B$25 | H12: =H11+E12-G12 | I12: =D12/Annahmen!$B$8
A13: 10 | B13: =MIN(Annahmen!$B$17,ROUND(Annahmen!$B$15*(1+Annahmen!$B$16)^(10-1),0)) | C13: =ROUND(D12*Annahmen!$B$20,0) | D13: =D12+B13-C13 | E13: =D13*Annahmen!$B$11 | F13: =E13*12 | G13: =B13*Annahmen!$B$25 | H13: =H12+E13-G13 | I13: =D13/Annahmen!$B$8
A14: 11 | B14: =MIN(Annahmen!$B$17,ROUND(Annahmen!$B$15*(1+Annahmen!$B$16)^(11-1),0)) | C14: =ROUND(D13*Annahmen!$B$20,0) | D14: =D13+B14-C14 | E14: =D14*Annahmen!$B$11 | F14: =E14*12 | G14: =B14*Annahmen!$B$25 | H14: =H13+E14-G14 | I14: =D14/Annahmen!$B$8
A15: 12 | B15: =MIN(Annahmen!$B$17,ROUND(Annahmen!$B$15*(1+Annahmen!$B$16)^(12-1),0)) | C15: =ROUND(D14*Annahmen!$B$20,0) | D15: =D14+B15-C15 | E15: =D15*Annahmen!$B$11 | F15: =E15*12 | G15: =B15*Annahmen!$B$25 | H15: =H14+E15-G15 | I15: =D15/Annahmen!$B$8
A16: 13 | B16: =MIN(Annahmen!$B$17,ROUND(Annahmen!$B$15*(1+Annahmen!$B$16)^(13-1),0)) | C16: =ROUND(D15*Annahmen!$B$20,0) | D16: =D15+B16-C16 | E16: =D16*Annahmen!$B$11 | F16: =E16*12 | G16: =B16*Annahmen!$B$25 | H16: =H15+E16-G16 | I16: =D16/Annahmen!$B$8
A17: 14 | B17: =MIN(Annahmen!$B$17,ROUND(Annahmen!$B$15*(1+Annahmen!$B$16)^(14-1),0)) | C17: =ROUND(D16*Annahmen!$B$20,0) | D17: =D16+B17-C17 | E17: =D17*Annahmen!$B$11 | F17: =E17*12 | G17: =B17*Annahmen!$B$25 | H17: =H16+E17-G17 | I17: =D17/Annahmen!$B$8
A18: 15 | B18: =MIN(Annahmen!$B$17,ROUND(Annahmen!$B$15*(1+Annahmen!$B$16)^(15-1),0)) | C18: =ROUND(D17*Annahmen!$B$20,0) | D18: =D17+B18-C18 | E18: =D18*Annahmen!$B$11 | F18: =E18*12 | G18: =B18*Annahmen!$B$25 | H18: =H17+E18-G18 | I18: =D18/Annahmen!$B$8
A19: 16 | B19: =MIN(Annahmen!$B$17,ROUND(Annahmen!$B$15*(1+Annahmen!$B$16)^(16-1),0)) | C19: =ROUND(D18*Annahmen!$B$20,0) | D19: =D18+B19-C19 | E19: =D19*Annahmen!$B$11 | F19: =E19*12 | G19: =B19*Annahmen!$B$25 | H19: =H18+E19-G19 | I19: =D19/Annahmen!$B$8
A20: 17 | B20: =MIN(Annahmen!$B$17,ROUND(Annahmen!$B$15*(1+Annahmen!$B$16)^(17-1),0)) | C20: =ROUND(D19*Annahmen!$B$20,0) | D20: =D19+B20-C20 | E20: =D20*Annahmen!$B$11 | F20: =E20*12 | G20: =B20*Annahmen!$B$25 | H20: =H19+E20-G20 | I20: =D20/Annahmen!$B$8
A21: 18 | B21: =MIN(Annahmen!$B$17,ROUND(Annahmen!$B$15*(1+Annahmen!$B$16)^(18-1),0)) | C21: =ROUND(D20*Annahmen!$B$20,0) | D21: =D20+B21-C21 | E21: =D21*Annahmen!$B$11 | F21: =E21*12 | G21: =B21*Annahmen!$B$25 | H21: =H20+E21-G21 | I21: =D21/Annahmen!$B$8
A22: 19 | B22: =MIN(Annahmen!$B$17,ROUND(Annahmen!$B$15*(1+Annahmen!$B$16)^(19-1),0)) | C22: =ROUND(D21*Annahmen!$B$20,0) | D22: =D21+B22-C22 | E22: =D22*Annahmen!$B$11 | F22: =E22*12 | G22: =B22*Annahmen!$B$25 | H22: =H21+E22-G22 | I22: =D22/Annahmen!$B$8
A23: 20 | B23: =MIN(Annahmen!$B$17,ROUND(Annahmen!$B$15*(1+Annahmen!$B$16)^(20-1),0)) | C23: =ROUND(D22*Annahmen!$B$20,0) | D23: =D22+B23-C23 | E23: =D23*Annahmen!$B$11 | F23: =E23*12 | G23: =B23*Annahmen!$B$25 | H23: =H22+E23-G23 | I23: =D23/Annahmen!$B$8
A24: 21 | B24: =MIN(Annahmen!$B$17,ROUND(Annahmen!$B$15*(1+Annahmen!$B$16)^(21-1),0)) | C24: =ROUND(D23*Annahmen!$B$20,0) | D24: =D23+B24-C24 | E24: =D24*Annahmen!$B$11 | F24: =E24*12 | G24: =B24*Annahmen!$B$25 | H24: =H23+E24-G24 | I24: =D24/Annahmen!$B$8
A25: 22 | B25: =MIN(Annahmen!$B$17,ROUND(Annahmen!$B$15*(1+Annahmen!$B$16)^(22-1),0)) | C25: =ROUND(D24*Annahmen!$B$20,0) | D25: =D24+B25-C25 | E25: =D25*Annahmen!$B$11 | F25: =E25*12 | G25: =B25*Annahmen!$B$25 | H25: =H24+E25-G25 | I25: =D25/Annahmen!$B$8
A26: 23 | B26: =MIN(Annahmen!$B$17,ROUND(Annahmen!$B$15*(1+Annahmen!$B$16)^(23-1),0)) | C26: =ROUND(D25*Annahmen!$B$20,0) | D26: =D25+B26-C26 | E26: =D26*Annahmen!$B$11 | F26: =E26*12 | G26: =B26*Annahmen!$B$25 | H26: =H25+E26-G26 | I26: =D26/Annahmen!$B$8
A27: 24 | B27: =MIN(Annahmen!$B$17,ROUND(Annahmen!$B$15*(1+Annahmen!$B$16)^(24-1),0)) | C27: =ROUND(D26*Annahmen!$B$20,0) | D27: =D26+B27-C27 | E27: =D27*Annahmen!$B$11 | F27: =E27*12 | G27: =B27*Annahmen!$B$25 | H27: =H26+E27-G27 | I27: =D27/Annahmen!$B$8
A28: 25 | B28: =MIN(Annahmen!$B$17,ROUND(Annahmen!$B$15*(1+Annahmen!$B$16)^(25-1),0)) | C28: =ROUND(D27*Annahmen!$B$20,0) | D28: =D27+B28-C28 | E28: =D28*Annahmen!$B$11 | F28: =E28*12 | G28: =B28*Annahmen!$B$25 | H28: =H27+E28-G28 | I28: =D28/Annahmen!$B$8
A29: 26 | B29: =MIN(Annahmen!$B$17,ROUND(Annahmen!$B$15*(1+Annahmen!$B$16)^(26-1),0)) | C29: =ROUND(D28*Annahmen!$B$20,0) | D29: =D28+B29-C29 | E29: =D29*Annahmen!$B$11 | F29: =E29*12 | G29: =B29*Annahmen!$B$25 | H29: =H28+E29-G29 | I29: =D29/Annahmen!$B$8
A30: 27 | B30: =MIN(Annahmen!$B$17,ROUND(Annahmen!$B$15*(1+Annahmen!$B$16)^(27-1),0)) | C30: =ROUND(D29*Annahmen!$B$20,0) | D30: =D29+B30-C30 | E30: =D30*Annahmen!$B$11 | F30: =E30*12 | G30: =B30*Annahmen!$B$25 | H30: =H29+E30-G30 | I30: =D30/Annahmen!$B$8
A31: 28 | B31: =MIN(Annahmen!$B$17,ROUND(Annahmen!$B$15*(1+Annahmen!$B$16)^(28-1),0)) | C31: =ROUND(D30*Annahmen!$B$20,0) | D31: =D30+B31-C31 | E31: =D31*Annahmen!$B$11 | F31: =E31*12 | G31: =B31*Annahmen!$B$25 | H31: =H30+E31-G31 | I31: =D31/Annahmen!$B$8
A32: 29 | B32: =MIN(Annahmen!$B$17,ROUND(Annahmen!$B$15*(1+Annahmen!$B$16)^(29-1),0)) | C32: =ROUND(D31*Annahmen!$B$20,0) | D32: =D31+B32-C32 | E32: =D32*Annahmen!$B$11 | F32: =E32*12 | G32: =B32*Annahmen!$B$25 | H32: =H31+E32-G32 | I32: =D32/Annahmen!$B$8
A33: 30 | B33: =MIN(Annahmen!$B$17,ROUND(Annahmen!$B$15*(1+Annahmen!$B$16)^(30-1),0)) | C33: =ROUND(D32*Annahmen!$B$20,0) | D33: =D32+B33-C33 | E33: =D33*Annahmen!$B$11 | F33: =E33*12 | G33: =B33*Annahmen!$B$25 | H33: =H32+E33-G33 | I33: =D33/Annahmen!$B$8
A34: 31 | B34: =MIN(Annahmen!$B$17,ROUND(Annahmen!$B$15*(1+Annahmen!$B$16)^(31-1),0)) | C34: =ROUND(D33*Annahmen!$B$20,0) | D34: =D33+B34-C34 | E34: =D34*Annahmen!$B$11 | F34: =E34*12 | G34: =B34*Annahmen!$B$25 | H34: =H33+E34-G34 | I34: =D34/Annahmen!$B$8
A35: 32 | B35: =MIN(Annahmen!$B$17,ROUND(Annahmen!$B$15*(1+Annahmen!$B$16)^(32-1),0)) | C35: =ROUND(D34*Annahmen!$B$20,0) | D35: =D34+B35-C35 | E35: =D35*Annahmen!$B$11 | F35: =E35*12 | G35: =B35*Annahmen!$B$25 | H35: =H34+E35-G35 | I35: =D35/Annahmen!$B$8
A36: 33 | B36: =MIN(Annahmen!$B$17,ROUND(Annahmen!$B$15*(1+Annahmen!$B$16)^(33-1),0)) | C36: =ROUND(D35*Annahmen!$B$20,0) | D36: =D35+B36-C36 | E36: =D36*Annahmen!$B$11 | F36: =E36*12 | G36: =B36*Annahmen!$B$25 | H36: =H35+E36-G36 | I36: =D36/Annahmen!$B$8
A37: 34 | B37: =MIN(Annahmen!$B$17,ROUND(Annahmen!$B$15*(1+Annahmen!$B$16)^(34-1),0)) | C37: =ROUND(D36*Annahmen!$B$20,0) | D37: =D36+B37-C37 | E37: =D37*Annahmen!$B$11 | F37: =E37*12 | G37: =B37*Annahmen!$B$25 | H37: =H36+E37-G37 | I37: =D37/Annahmen!$B$8
A38: 35 | B38: =MIN(Annahmen!$B$17,ROUND(Annahmen!$B$15*(1+Annahmen!$B$16)^(35-1),0)) | C38: =ROUND(D37*Annahmen!$B$20,0) | D38: =D37+B38-C38 | E38: =D38*Annahmen!$B$11 | F38: =E38*12 | G38: =B38*Annahmen!$B$25 | H38: =H37+E38-G38 | I38: =D38/Annahmen!$B$8
A39: 36 | B39: =MIN(Annahmen!$B$17,ROUND(Annahmen!$B$15*(1+Annahmen!$B$16)^(36-1),0)) | C39: =ROUND(D38*Annahmen!$B$20,0) | D39: =D38+B39-C39 | E39: =D39*Annahmen!$B$11 | F39: =E39*12 | G39: =B39*Annahmen!$B$25 | H39: =H38+E39-G39 | I39: =D39/Annahmen!$B$8

Sheet Szenarien
A1: Was bringt welche Kundenzahl?
A2: Jahresumsatz bei unterschiedlichen Preispunkten und Abo-Zahlen.
A4: Abos ↓ / Preis → | B4: 49 | C4: 79 | D4: 99 | E4: 149 | F4: 199
A5: 50 | B5: =$A5*B$4*12 | C5: =$A5*C$4*12 | D5: =$A5*D$4*12 | E5: =$A5*E$4*12 | F5: =$A5*F$4*12
A6: 100 | B6: =$A6*B$4*12 | C6: =$A6*C$4*12 | D6: =$A6*D$4*12 | E6: =$A6*E$4*12 | F6: =$A6*F$4*12
A7: 250 | B7: =$A7*B$4*12 | C7: =$A7*C$4*12 | D7: =$A7*D$4*12 | E7: =$A7*E$4*12 | F7: =$A7*F$4*12
A8: 500 | B8: =$A8*B$4*12 | C8: =$A8*C$4*12 | D8: =$A8*D$4*12 | E8: =$A8*E$4*12 | F8: =$A8*F$4*12
A9: 1000 | B9: =$A9*B$4*12 | C9: =$A9*C$4*12 | D9: =$A9*D$4*12 | E9: =$A9*E$4*12 | F9: =$A9*F$4*12
A10: 1500 | B10: =$A10*B$4*12 | C10: =$A10*C$4*12 | D10: =$A10*D$4*12 | E10: =$A10*E$4*12 | F10: =$A10*F$4*12
A13: Break-even-Betrachtung
A14: Monatliche Fixkosten (Team, Technik, Recht) | B14: 8000
A15: Benötigte Abos für Kostendeckung | B15: =ROUNDUP(B14/Annahmen!$B$11,0)
A16: Entspricht Marktdurchdringung von | B16: =B15/Annahmen!$B$8
A17: Auftragswert, ab dem sich das Abo für den Anbieter rechnet | B17: =Annahmen!$B$11*12
A18: → Ein einziger vermittelter Event-Auftrag (ca. 1.440 €) deckt das Jahresabo.

Sheet Hinweise
A1: Quellen und Annahmen
A3: Belegte Zahlen
A4: 5.330 Unternehmen im WZ 80.1 'Wach- und Sicherheitsdienste', Stichtag Sept. 2023.
A5: Quelle: Statistisches Bundesamt / Bewacherregister, Strukturerhebung Dienstleistungsbereich.
A6: Top 25 erwirtschaften 5,63 Mrd. € = rund 40 % des Marktvolumens ohne Geld- und Wertlogistik.
A7: Quelle: Lünendonk-Liste 2026, Führende Sicherheitsdienstleister in Deutschland.
A8: Branchenumsatz 2024: 14,02 Mrd. €. BDSW-Prognose 2025: rund 14,75 Mrd. €.
A10: Eigene Annahmen — nicht belegt, bitte selbst schärfen
A11: Adressierbarer Anteil 45 %: Betriebe mit Event- oder Kurzfristgeschäft. Langfristige
A12: Werkschutz-Rahmenverträge laufen über Ausschreibungen, nicht über einen Marktplatz.
A13: Churn 4 % pro Monat: typisch für KMU-SaaS mit monatlicher Kündbarkeit. Diese Zahl
A14: entscheidet über das gesamte Modell — bei 8 % halbiert sich der Lifetime Value.
... A21: Jahresverträge. Bei 12-Monats-Bindung sinkt der Churn stark, die Abschlussquote aber auch.
